Sumador1Bit.v
module Sumador1Bit (
    input A,
    input B,
    input Cin,
    output S,
    output Cout
);

    wire x_ab;
    wire cout_t;
    wire a_ab;
    
    xor(x_ab,A, B);
    and(cout_t,x_ab, Cin);
    and(a_ab,A, B);
    xor(S,x_ab,Cin);
    or(Cout,cout_t,a_ab);

endmodule

src/Sumador1Bit_tb.v
`timescale 1ns / 1ps
`include "src/Sumador1Bit.v"

module Sumador1Bit_tb;

    // Entradas del módulo
    reg A;
    reg B;
    reg Cin;

    // Salidas del módulo
    wire S;
    wire Cout;

    // Instancia del módulo bajo prueba (DUT - Device Under Test)
    Sumador1Bit dut (
        .A(A),
        .B(B),
        .Cin(Cin),
        .S(S),
        .Cout(Cout)
    );

    // Proceso de prueba
    initial begin
        // Encabezado en la simulación
        $dumpfile("suma_1_bit.vcd");   // Nombre del archivo de señales
        $dumpvars(0, Sumador1Bit_tb); // Volcar todas las variables del testbench
        $display("Time\tA\tB\tCin\t|\tS\tCout");
        $monitor("%0t\t%b\t%b\t%b\t|\t%b\t%b", $time, A, B, Cin, S, Cout);

        // Prueba de todas las combinaciones posibles
        A = 0; B = 0; Cin = 0; #10;  // Caso 1: 000
        A = 0; B = 0; Cin = 1; #10;  // Caso 2: 001
        A = 0; B = 1; Cin = 0; #10;  // Caso 3: 010
        A = 0; B = 1; Cin = 1; #10;  // Caso 4: 011
        A = 1; B = 0; Cin = 0; #10;  // Caso 5: 100
        A = 1; B = 0; Cin = 1; #10;  // Caso 6: 101
        A = 1; B = 1; Cin = 0; #10;  // Caso 7: 110
        A = 1; B = 1; Cin = 1; #10;  // Caso 8: 111

        // Fin de la simulación
        $finish;
    end

endmodule

src/assets/simulations/suma_1_bit.vcd
$date
	Mon Dec 16 18:47:07 2024
$end
$version
	Icarus Verilog
$end
$timescale
	1ps
$end
$scope module Sumador1Bit_tb $end
$var wire 1 ! S $end
$var wire 1 " Cout $end
$var reg 1 # A $end
$var reg 1 $ B $end
$var reg 1 % Cin $end
$scope module dut $end
$var wire 1 # A $end
$var wire 1 $ B $end
$var wire 1 % Cin $end
$var wire 1 " Cout $end
$var wire 1 ! S $end
$var wire 1 & a_ab $end
$var wire 1 ' cout_t $end
$var wire 1 ( x_ab $end
$upscope $end
$upscope $end
$enddefinitions $end
#0
$dumpvars
0(
0'
0&
0%
0$
0#
0"
0!
$end
#10000
1!
1%
#20000
1(
0%
1$
#30000
1"
1'
0!
1%
#40000
0"
0'
1!
0%
0$
1#
#50000
1"
1'
0!
1%
#60000
0'
0(
1&
0%
1$
#70000
1!
1%
